Workbook

Sheet 試算条件
B1: 試算条件
B3: ■ 単価（万円/人月）
B4: 区分 | C4: 国内BP単価（原価） | D4: ODC単価（原価） | E4: 国内BP単価（売値） | F4: ODC単価（売値）
B5: 保守 | C5: 80 | D5: 50 | E5: 115 | F5: 85
B6: 開発 | C6: 80 | D6: 50 | E6: 115 | F6: 85
B8: ■ 全体設定
B9: 項目 | C9: 設定値 | D9: 備考
B10: 当社割合（SCSK担当割合） | C10: 0 | D10: ←当社が担当する割合。他社割合＝1−当社割合
B11: 業務移管コスト計上方式 | C11: 売上計上（顧客請求） | D11: ←"原価計上（当社持ち出し）" または "売上計上（顧客請求）"
B13: ■ 試算因子
B14: 項目 | C14: 1年目（27年度） | D14: 2年目（28年度） | E14: 3年目（29年度） | F14: 備考
B15: 顧客向けコスト低減率（当社担当分） | C15: 0.1 | D15: 0.2 | E15: 0.35
B16: 顧客向けコスト低減率（他社担当分） | C16: 0 | D16: 0.15 | E16: 0.3
B17: 移管領域の実業務割合 | C17: 0.5 | D17: 1 | E17: 1 | F17: ←1年目は段階的移行のため50%。当社の実効割合に乗算
B18: 業務移管コスト率（他社保守のみ適用） | C18: 0.3 | D18: 0 | E18: 0 | F18: ←業務移管コスト。他社保守1年目のみ適用
B19: ODC活用率（当社担当分） | C19: 0.1 | D19: 0.25 | E19: 0.5 | F19: ←当社担当分のODC活用率 ※WK白地シート準拠
B20: ODC活用率（他社担当分） | C20: 0 | D20: 0.1 | E20: 0.3 | F20: ←他社担当分のODC活用率 ※WK白地シート準拠
B21: ODC単価率（ODC/国内） | C21: 0.625 | D21: 0.625 | E21: 0.625 | F21: ←ODC50万/国内80万
B22: 生産性向上率（保守）当社担当分・ソーシング | C22: 0.1 | D22: 0.2 | E22: 0.2 | F22: ソーシング効果分 ※WK白地シート準拠
B23: 生産性向上率（保守）当社担当分・AI活用 | C23: 0 | D23: 0.1 | E23: 0.23 | F23: AI活用効果分 ※WK白地シート準拠
B24: 生産性向上率（開発）当社担当分・ソーシング | C24: 0.1 | D24: 0.2 | E24: 0.2 | F24: ソーシング効果分 ※WK白地シート準拠
B25: 生産性向上率（開発）当社担当分・AI活用 | C25: 0 | D25: 0.15 | E25: 0.3 | F25: AI活用効果分 ※WK白地シート準拠
B26: 生産性向上率（保守）他社担当分・ソーシング | C26: 0.05 | D26: 0.1 | E26: 0.2 | F26: ソーシング効果分 ※WK白地シート準拠
B27: 生産性向上率（保守）他社担当分・AI活用 | C27: 0 | D27: 0.1 | E27: 0.15 | F27: AI活用効果分 ※WK白地シート準拠
B28: 生産性向上率（開発）他社担当分・ソーシング | C28: 0.05 | D28: 0.1 | E28: 0.2 | F28: ソーシング効果分 ※WK白地シート準拠
... B35: 既存パートナー原価率 | C35: 0.95 | D35: 0.95 | E35: 0.95 | F35: 既存パートナー分の売上に対する原価率(粗利10%想定)
B36: 実効原価率 | C36: =C33*C35+(1-C33)*C34 | D36: =D33*D35+(1-D33)*D34 | E36: =E33*E35+(1-E33)*E34 | F36: ＝既存パートナー比率×既存パートナー原価率＋(1−既存パートナー比率)×通常原価率

Sheet セグメント見積
B1: セグメント見積コスト試算シート（4区分・当社割合ベース）
B3: ■ A. セグメント基本情報（入力）
B4: 項目 | C4: 設定値 | D4: 備考
B5: セグメント名 | C5: 共通マスタ・周辺
B6: 分類 | C6: ②COB白地 | D6: セグメントの分類区分（①COB既存・隣接／②COB白地／③デジタル から選択）
B7: 経済安保対象（ODC除外） | C7: 113.35 | D7: ◎=除外 / ×=可（保険金・マリン等は◎）
B8: 保守合計（億円）※基準値 | C8: 0.84 | D8: ←試算の基準値。年度共通
B9: 開発合計（億円）※基準値 | C9: 2.13 | D9: ←試算の基準値。年度共通
B11: ■ B. 当社割合による按分結果（百万円）※目標値（基準値ベース）
B12: 区分 | C12: 金額（百万円） | D12: 備考
B13: 当社保守 | C13: =C8*100*試算条件!$C$10 | D13: ＝保守基準値 × 当社割合（Y1は移管過渡期のため実業務は50%）
B14: 当社開発 | C14: =C9*100*試算条件!$C$10 | D14: ＝開発基準値 × 当社割合（Y1は移管過渡期のため実業務は50%）
B15: 他社保守 | C15: =C8*100*(1-試算条件!$C$10) | D15: ＝保守基準値 × 他社割合（Y1は当社移管未了分を他社が担当）
B16: 他社開発 | C16: =C9*100*(1-試算条件!$C$10) | D16: ＝開発基準値 × 他社割合（Y1は当社移管未了分を他社が担当）
B17: ※C〜F各セクションでは「移管領域の実業務割合」を考慮した年度別の実効値で計算されます。
B19: ■ C. 当社保守 損益シミュレーション（百万円）
B20: 区分 | C20: 1年目 | D20: 2年目 | E20: 3年目 | F20: 3年累計
B21: 売上（百万円） | C21: =$C$8*100*試算条件!$C$10*(1-試算条件!C15) | D21: =$C$8*100*試算条件!$C$10*(1-試算条件!D15) | E21: =$C$8*100*試算条件!$C$10*(1-試算条件!E15) | F21: =SUM(C21:E21)
B22: 原価_国内（百万円） | C22: =IF($C$6="②COB白地",$C$8*100*試算条件!$C$10*(1-(試算条件!C22+試算条件!C23))*(試算条件!C$33*試算条件!C$35+(1-試算条件!C$33)*試算条件!C$34*(1-試算条件!C19)),$C$8*100*試算条件!$C$10*(1-試算条件!C30)*(1-(試算条件!C22+試算条件!C23))*(1-試算条件!C19)) | D22: =IF($C$6="②COB白地",$C$8*100*試算条件!$C$10*(1-(試算条件!D22+試算条件!D23))*(試算条件!D$33*試算条件!D$35+(1-試算条件!D$33)*試算条件!D$34*(1-試算条件!D19)),$C$8*100*試算条件!$C$10*(1-試算条件!D30)*(1-(試算条件!D22+試算条件!D23))*(1-試算条件!D19)) | E22: =IF($C$6="②COB白地",$C$8*100*試算条件!$C$10*(1-(試算条件!E22+試算条件!E23))*(試算条件!E$33*試算条件!E$35+(1-試算条件!E$33)*試算条件!E$34*(1-試算条件!E19)),$C$8*100*試算条件!$C$10*(1-試算条件!E30)*(1-(試算条件!E22+試算条件!E23))*(1-試算条件!E19)) | F22: =SUM(C22:E22)
B23: 原価_ODC（百万円） | C23: =IF($C$6="②COB白地",$C$8*100*試算条件!$C$10*(1-(試算条件!C22+試算条件!C23))*(1-試算条件!C$33)*試算条件!C$34*試算条件!C19*試算条件!C21,$C$8*100*試算条件!$C$10*(1-試算条件!C30)*(1-(試算条件!C22+試算条件!C23))*試算条件!C19*試算条件!C21) | D23: =IF($C$6="②COB白地",$C$8*100*試算条件!$C$10*(1-(試算条件!D22+試算条件!D23))*(1-試算条件!D$33)*試算条件!D$34*試算条件!D19*試算条件!D21,$C$8*100*試算条件!$C$10*(1-試算条件!D30)*(1-(試算条件!D22+試算条件!D23))*試算条件!D19*試算条件!D21) | E23: =IF($C$6="②COB白地",$C$8*100*試算条件!$C$10*(1-(試算条件!E22+試算条件!E23))*(1-試算条件!E$33)*試算条件!E$34*試算条件!E19*試算条件!E21,$C$8*100*試算条件!$C$10*(1-試算条件!E30)*(1-(試算条件!E22+試算条件!E23))*試算条件!E19*試算条件!E21) | F23: =SUM(C23:E23)
B24: 業務移管コスト（百万円）※他社保守Y1のみ | C24: 0 | D24: 0 | E24: 0 | F24: =SUM(C24:E24)
B25: 売上加算分（顧客請求時のみ） | C25: 0 | D25: 0 | E25: 0 | F25: =SUM(C25:E25)
B26: 売上（調整後・百万円） | C26: =C21+C25 | D26: =D21+D25 | E26: =E21+E25 | F26: =SUM(C26:E26)
B27: 原価合計（百万円） | C27: =C22+C23 | D27: =D22+D23 | E27: =E22+E23 | F27: =SUM(C27:E27)
B28: 粗利（百万円） | C28: =C26-C27 | D28: =D26-D27 | E28: =E26-E27 | F28: =SUM(C28:E28)
B29: 粗利率 | C29: =IFERROR(C28/C26,0) | D29: =IFERROR(D28/D26,0) | E29: =IFERROR(E28/E26,0) | F29: =IFERROR(F28/F26,0)
B31: ■ D. 当社開発 損益シミュレーション（百万円）
B32: 区分 | C32: 1年目 | D32: 2年目 | E32: 3年目 | F32: 3年累計
B33: 売上（百万円） | C33: =$C$9*100*試算条件!$C$10*(1-試算条件!C15) | D33: =$C$9*100*試算条件!$C$10*(1-試算条件!D15) | E33: =$C$9*100*試算条件!$C$10*(1-試算条件!E15) | F33: =SUM(C33:E33)
B34: 原価_国内（百万円） | C34: =IF($C$6="②COB白地",$C$9*100*試算条件!$C$10*(1-(試算条件!C24+試算条件!C25))*(試算条件!C$33*試算条件!C$35+(1-試算条件!C$33)*試算条件!C$34*(1-試算条件!C19)),$C$9*100*試算条件!$C$10*(1-試算条件!C31)*(1-(試算条件!C24+試算条件!C25))*(1-試算条件!C19)) | D34: =IF($C$6="②COB白地",$C$9*100*試算条件!$C$10*(1-(試算条件!D24+試算条件!D25))*(試算条件!D$33*試算条件!D$35+(1-試算条件!D$33)*試算条件!D$34*(1-試算条件!D19)),$C$9*100*試算条件!$C$10*(1-試算条件!D31)*(1-(試算条件!D24+試算条件!D25))*(1-試算条件!D19)) | E34: =IF($C$6="②COB白地",$C$9*100*試算条件!$C$10*(1-(試算条件!E24+試算条件!E25))*(試算条件!E$33*試算条件!E$35+(1-試算条件!E$33)*試算条件!E$34*(1-試算条件!E19)),$C$9*100*試算条件!$C$10*(1-試算条件!E31)*(1-(試算条件!E24+試算条件!E25))*(1-試算条件!E19)) | F34: =SUM(C34:E34)
B35: 原価_ODC（百万円） | C35: =IF($C$6="②COB白地",$C$9*100*試算条件!$C$10*(1-(試算条件!C24+試算条件!C25))*(1-試算条件!C$33)*試算条件!C$34*試算条件!C19*試算条件!C21,$C$9*100*試算条件!$C$10*(1-試算条件!C31)*(1-(試算条件!C24+試算条件!C25))*試算条件!C19*試算条件!C21) | D35: =IF($C$6="②COB白地",$C$9*100*試算条件!$C$10*(1-(試算条件!D24+試算条件!D25))*(1-試算条件!D$33)*試算条件!D$34*試算条件!D19*試算条件!D21,$C$9*100*試算条件!$C$10*(1-試算条件!D31)*(1-(試算条件!D24+試算条件!D25))*試算条件!D19*試算条件!D21) | E35: =IF($C$6="②COB白地",$C$9*100*試算条件!$C$10*(1-(試算条件!E24+試算条件!E25))*(1-試算条件!E$33)*試算条件!E$34*試算条件!E19*試算条件!E21,$C$9*100*試算条件!$C$10*(1-試算条件!E31)*(1-(試算条件!E24+試算条件!E25))*試算条件!E19*試算条件!E21) | F35: =SUM(C35:E35)
B36: 業務移管コスト（百万円）※他社保守Y1のみ | C36: 0 | D36: 0 | E36: 0 | F36: =SUM(C36:E36)
B37: 売上加算分（顧客請求時のみ） | C37: 0 | D37: 0 | E37: 0 | F37: =SUM(C37:E37)
B38: 売上（調整後・百万円） | C38: =C33+C37 | D38: =D33+D37 | E38: =E33+E37 | F38: =SUM(C38:E38)
B39: 原価合計（百万円） | C39: =C34+C35 | D39: =D34+D35 | E39: =E34+E35 | F39: =SUM(C39:E39)
B40: 粗利（百万円） | C40: =C38-C39 | D40: =D38-D39 | E40: =E38-E39 | F40: =SUM(C40:E40)
B41: 粗利率 | C41: =IFERROR(C40/C38,0) | D41: =IFERROR(D40/D38,0) | E41: =IFERROR(E40/E38,0) | F41: =IFERROR(F40/F38,0)
B43: ■ E. 他社保守 損益シミュレーション（百万円）※業務移管コスト適用
B44: 区分 | C44: 1年目 | D44: 2年目 | E44: 3年目 | F44: 3年累計
B45: 売上（百万円） | C45: =$C$8*100*(1-試算条件!$C$10)*試算条件!C17*(1-試算条件!C16) | D45: =$C$8*100*(1-試算条件!$C$10)*試算条件!D17*(1-試算条件!D16) | E45: =$C$8*100*(1-試算条件!$C$10)*試算条件!E17*(1-試算条件!E16) | F45: =SUM(C45:E45)
B46: 原価_国内（百万円） | C46: IF($C$6="②COB白地",$C$8*100*(1-試算条件!$C$10)*試算条件!C17*(1-(試算条件!C26+試算条件!C27))*(試算条件!C$33*試算条件!C$35+(1-試算条件!C$33)*試算条件!C$34)*(1-試算条件!C20),$C$8*100*(1-試算条件!$C$10)*試算条件!C17*(1-試算条件!C30)*(1-(試算条件!C26+試算条件!C27))*(1-試算条件!C20)) | D46: IF($C$6="②COB白地",$C$8*100*(1-試算条件!$C$10)*試算条件!D17*(1-(試算条件!D26+試算条件!D27))*(試算条件!C$33*試算条件!C$35+(1-試算条件!C$33)*試算条件!C$34)*(1-試算条件!D20),$C$8*100*(1-試算条件!$C$10)*試算条件!D17*(1-試算条件!C30)*(1-(試算条件!D26+試算条件!D27))*(1-試算条件!D20)) | E46: IF($C$6="②COB白地",$C$8*100*(1-試算条件!$C$10)*試算条件!E17*(1-(試算条件!E26+試算条件!E27))*(試算条件!C$33*試算条件!C$35+(1-試算条件!C$33)*試算条件!C$34)*(1-試算条件!E20),$C$8*100*(1-試算条件!$C$10)*試算条件!E17*(1-試算条件!C30)*(1-(試算条件!E26+試算条件!E27))*(1-試算条件!E20)) | F46: =SUM(C46:E46)
B47: 原価_ODC（百万円） | C47: IF($C$6="②COB白地",$C$8*100*(1-試算条件!$C$10)*試算条件!C17*(1-(試算条件!C26+試算条件!C27))*(試算条件!C$33*試算条件!C$35+(1-試算条件!C$33)*試算条件!C$34)*試算条件!C20*試算条件!C21,$C$8*100*(1-試算条件!$C$10)*試算条件!C17*(1-試算条件!C30)*(1-(試算条件!C26+試算条件!C27))*試算条件!C20*試算条件!C21) | D47: IF($C$6="②COB白地",$C$8*100*(1-試算条件!$C$10)*試算条件!D17*(1-(試算条件!D26+試算条件!D27))*(試算条件!C$33*試算条件!C$35+(1-試算条件!C$33)*試算条件!C$34)*試算条件!D20*試算条件!D21,$C$8*100*(1-試算条件!$C$10)*試算条件!D17*(1-試算条件!C30)*(1-(試算条件!D26+試算条件!D27))*試算条件!D20*試算条件!D21) | E47: IF($C$6="②COB白地",$C$8*100*(1-試算条件!$C$10)*試算条件!E17*(1-(試算条件!E26+試算条件!E27))*(試算条件!C$33*試算条件!C$35+(1-試算条件!C$33)*試算条件!C$34)*試算条件!E20*試算条件!E21,$C$8*100*(1-試算条件!$C$10)*試算条件!E17*(1-試算条件!C30)*(1-(試算条件!E26+試算条件!E27))*試算条件!E20*試算条件!E21) | F47: =SUM(C47:E47)
B48: 業務移管コスト（百万円）※他社保守Y1のみ | C48: =$C$8*100*(1-試算条件!$C$10)*試算条件!C18 | D48: =$C$8*100*(1-試算条件!$C$10)*試算条件!D18 | E48: =$C$8*100*(1-試算条件!$C$10)*試算条件!E18 | F48: =SUM(C48:E48)
B49: 売上加算分（顧客請求時のみ） | C49: =IF(試算条件!$C$11="売上計上（顧客請求）",C48,0) | D49: =IF(試算条件!$C$11="売上計上（顧客請求）",D48,0) | E49: =IF(試算条件!$C$11="売上計上（顧客請求）",E48,0) | F49: =SUM(C49:E49)
B50: 売上（調整後・百万円） | C50: =C45+C49 | D50: =D45+D49 | E50: =E45+E49 | F50: =SUM(C50:E50)
B51: 原価合計（百万円） | C51: =IF($C$6="②COB白地",C46+C47+C48*試算条件!C$36,C46+C47+C48*0.7) | D51: =IF($C$6="②COB白地",D46+D47+D48*試算条件!D$36,D46+D47+D48*0.7) | E51: =IF($C$6="②COB白地",E46+E47+E48*試算条件!E$36,E46+E47+E48*0.7) | F51: =SUM(C51:E51)
B52: 粗利（百万円） | C52: =C50-C51 | D52: =D50-D51 | E52: =E50-E51 | F52: =SUM(C52:E52)
B53: 粗利率 | C53: =IFERROR(C52/C50,0) | D53: =IFERROR(D52/D50,0) | E53: =IFERROR(E52/E50,0) | F53: =IFERROR(F52/F50,0)
B55: ■ F. 他社開発 損益シミュレーション（百万円）
B56: 区分 | C56: 1年目 | D56: 2年目 | E56: 3年目 | F56: 3年累計
B57: 売上（百万円） | C57: =$C$9*100*(1-試算条件!$C$10)*試算条件!C17*(1-試算条件!C16) | D57: =$C$9*100*(1-試算条件!$C$10)*試算条件!D17*(1-試算条件!D16) | E57: =$C$9*100*(1-試算条件!$C$10)*試算条件!E17*(1-試算条件!E16) | F57: =SUM(C57:E57)
B58: 原価_国内（百万円） | C58: IF($C$6="②COB白地",$C$9*100*(1-試算条件!$C$10)*試算条件!C17*(1-(試算条件!C28+試算条件!C29))*(試算条件!C$33*試算条件!C$35+(1-試算条件!C$33)*試算条件!C$34)*(1-試算条件!C20),$C$9*100*(1-試算条件!$C$10)*試算条件!C17*(1-試算条件!C31)*(1-(試算条件!C28+試算条件!C29))*(1-試算条件!C20)) | D58: IF($C$6="②COB白地",$C$9*100*(1-試算条件!$C$10)*試算条件!D17*(1-(試算条件!D28+試算条件!D29))*(試算条件!C$33*試算条件!C$35+(1-試算条件!C$33)*試算条件!C$34)*(1-試算条件!D20),$C$9*100*(1-試算条件!$C$10)*試算条件!D17*(1-試算条件!C31)*(1-(試算条件!D28+試算条件!D29))*(1-試算条件!D20)) | E58: IF($C$6="②COB白地",$C$9*100*(1-試算条件!$C$10)*試算条件!E17*(1-(試算条件!E28+試算条件!E29))*(試算条件!C$33*試算条件!C$35+(1-試算条件!C$33)*試算条件!C$34)*(1-試算条件!E20),$C$9*100*(1-試算条件!$C$10)*試算条件!E17*(1-試算条件!C31)*(1-(試算条件!E28+試算条件!E29))*(1-試算条件!E20)) | F58: =SUM(C58:E58)
B59: 原価_ODC（百万円） | C59: IF($C$6="②COB白地",$C$9*100*(1-試算条件!$C$10)*試算条件!C17*(1-(試算条件!C28+試算条件!C29))*(試算条件!C$33*試算条件!C$35+(1-試算条件!C$33)*試算条件!C$34)*試算条件!C20*試算条件!C21,$C$9*100*(1-試算条件!$C$10)*試算条件!C17*(1-試算条件!C31)*(1-(試算条件!C28+試算条件!C29))*試算条件!C20*試算条件!C21) | D59: IF($C$6="②COB白地",$C$9*100*(1-試算条件!$C$10)*試算条件!D17*(1-(試算条件!D28+試算条件!D29))*(試算条件!C$33*試算条件!C$35+(1-試算条件!C$33)*試算条件!C$34)*試算条件!D20*試算条件!D21,$C$9*100*(1-試算条件!$C$10)*試算条件!D17*(1-試算条件!C31)*(1-(試算条件!D28+試算条件!D29))*試算条件!D20*試算条件!D21) | E59: IF($C$6="②COB白地",$C$9*100*(1-試算条件!$C$10)*試算条件!E17*(1-(試算条件!E28+試算条件!E29))*(試算条件!C$33*試算条件!C$35+(1-試算条件!C$33)*試算条件!C$34)*試算条件!E20*試算条件!E21,$C$9*100*(1-試算条件!$C$10)*試算条件!E17*(1-試算条件!C31)*(1-(試算条件!E28+試算条件!E29))*試算条件!E20*試算条件!E21) | F59: =SUM(C59:E59)
B60: 業務移管コスト（百万円）※他社保守Y1のみ | C60: 0 | D60: 0 | E60: 0 | F60: =SUM(C60:E60)
B61: 売上加算分（顧客請求時のみ） | C61: 0 | D61: 0 | E61: 0 | F61: =SUM(C61:E61)
B62: 売上（調整後・百万円） | C62: =C57+C61 | D62: =D57+D61 | E62: =E57+E61 | F62: =SUM(C62:E62)
B63: 原価合計（百万円） | C63: =C58+C59 | D63: =D58+D59 | E63: =E58+E59 | F63: =SUM(C63:E63)
B64: 粗利（百万円） | C64: =C62-C63 | D64: =D62-D63 | E64: =E62-E63 | F64: =SUM(C64:E64)
B65: 粗利率 | C65: =IFERROR(C64/C62,0) | D65: =IFERROR(D64/D62,0) | E65: =IFERROR(E64/E62,0) | F65: =IFERROR(F64/F62,0)
B67: ■ G. 4区分サマリ（百万円）
B68: 区分 | C68: 1年目 売上 | D68: 2年目 売上 | E68: 3年目 売上 | F68: 1年目 粗利 | G68: 2年目 粗利 | H68: 3年目 粗利
B69: 当社保守 | C69: =C26 | D69: =D26 | E69: =E26 | F69: =C28 | G69: =D28 | H69: =E28
B70: 当社開発 | C70: =C38 | D70: =D38 | E70: =E38 | F70: =C40 | G70: =D40 | H70: =E40
B71: 他社保守 | C71: =C50 | D71: =D50 | E71: =E50 | F71: =C52 | G71: =D52 | H71: =E52
B72: 他社開発 | C72: =C62 | D72: =D62 | E72: =E62 | F72: =C64 | G72: =D64 | H72: =E64
B73: 合計 | C73: =SUM(C69:C72) | D73: =SUM(D69:D72) | E73: =SUM(E69:E72) | F73: =SUM(F69:F72) | G73: =SUM(G69:G72) | H73: =SUM(H69:H72)
B76: ■ H. 業務移管コスト計上方式 パターン比較（Year1・他社保守のみ・百万円）
B77: 項目 | C77: Pattern A（原価計上） | D77: Pattern B（売上計上） | E77: 差分（B−A）
B78: 業務移管コスト（他社保守Y1） | C78: =C48 | D78: =C48 | E78: =D78-C78
B79: Y1売上（他社保守のみ） | C79: =C45 | D79: =C45+C48 | E79: =D79-C79
B80: Y1原価（他社保守のみ） | C80: =C46+C47+C48 | D80: =C46+C47 | E80: =D80-C80
B81: Y1粗利（他社保守のみ） | C81: =C79-C80 | D81: =D79-D80 | E81: =D81-C81
B82: Y1粗利率（他社保守のみ） | C82: =IFERROR(C81/C79,0) | D82: =IFERROR(D81/D79,0) | E82: =D82-C82
